hatch_pin_jumpstarter/__init__.py
hatch_pin_jumpstarter/py.typed
hatch_pin_jumpstarter-0.1.0.dist-info/METADATA
hatch_pin_jumpstarter-0.1.0.dist-info/WHEEL
hatch_pin_jumpstarter-0.1.0.dist-info/entry_points.txt
hatch_pin_jumpstarter-0.1.0.dist-info/RECORD
